global_utils/__init__.py
global_utils/utils.py
handlers/__init__.py
handlers/hub_handler.py
handlers/model_handler.py
kan/__init__.py
kan/args.py
kan/kan.py
kan/version.py
kan/architectures/KKAN.py
kan/architectures/__init__.py
kan/architectures/conv.py
kan/architectures/gnn.py
kan/architectures/mlp.py
trainer/__init__.py
trainer/sft.py
trainer/trainer_args.py
mlx_kan-0.2.5.dist-info/LICENSE
mlx_kan-0.2.5.dist-info/METADATA
mlx_kan-0.2.5.dist-info/WHEEL
mlx_kan-0.2.5.dist-info/top_level.txt
mlx_kan-0.2.5.dist-info/RECORD
