Metadata-Version: 2.2
Name: mlx-kan
Version: 0.2.5
Summary: KAN: Kolmogorov–Arnold Networks on Apple silicon with MLX.
Home-page: https://github.com/Goekdeniz-Guelmez/mlx-kan
Author: Gökdeniz Gülmez
Author-email: goekdenizguelmez@gmail.com
License: Apache-2.0
Classifier: Programming Language :: Python :: 3.10
Classifier: Operating System :: MacOS :: MacOS X
Requires-Python: >=3.8
License-File: LICENSE
Requires-Dist: mlx>=0.18.1
Requires-Dist: numpy==2.0.1
Requires-Dist: setuptools==69.5.1
Requires-Dist: tqdm
Dynamic: author
Dynamic: author-email
Dynamic: classifier
Dynamic: description
Dynamic: description-content-type
Dynamic: home-page
Dynamic: license
Dynamic: requires-dist
Dynamic: requires-python
Dynamic: summary
